odoo/addons/account_invoice_report_due_list/README.rst
odoo/addons/account_invoice_report_due_list/__init__.py
odoo/addons/account_invoice_report_due_list/__manifest__.py
odoo/addons/account_invoice_report_due_list/i18n/account_invoice_report_due_list.pot
odoo/addons/account_invoice_report_due_list/i18n/es.po
odoo/addons/account_invoice_report_due_list/models/__init__.py
odoo/addons/account_invoice_report_due_list/models/account_invoice.py
odoo/addons/account_invoice_report_due_list/readme/CONTRIBUTORS.rst
odoo/addons/account_invoice_report_due_list/readme/DESCRIPTION.rst
odoo/addons/account_invoice_report_due_list/readme/USAGE.rst
odoo/addons/account_invoice_report_due_list/static/description/icon.png
odoo/addons/account_invoice_report_due_list/static/description/icon.svg
odoo/addons/account_invoice_report_due_list/static/description/index.html
odoo/addons/account_invoice_report_due_list/tests/__init__.py
odoo/addons/account_invoice_report_due_list/tests/test_invoice_report_due_list.py
odoo/addons/account_invoice_report_due_list/views/account_invoice_view.xml
odoo/addons/account_invoice_report_due_list/views/report_invoice.xml
odoo11_addon_account_invoice_report_due_list-11.0.1.2.0.dist-info/METADATA
odoo11_addon_account_invoice_report_due_list-11.0.1.2.0.dist-info/WHEEL
odoo11_addon_account_invoice_report_due_list-11.0.1.2.0.dist-info/top_level.txt
odoo11_addon_account_invoice_report_due_list-11.0.1.2.0.dist-info/RECORD
